tests/__init__.py
tests/test_tree_values.py
tree_values/__init__.py
tree_values/tree_values.py
tree_values_viewer-0.1.16.dist-info/LICENSE
tree_values_viewer-0.1.16.dist-info/METADATA
tree_values_viewer-0.1.16.dist-info/WHEEL
tree_values_viewer-0.1.16.dist-info/entry_points.txt
tree_values_viewer-0.1.16.dist-info/top_level.txt
tree_values_viewer-0.1.16.dist-info/RECORD
