Metadata-Version: 2.1
Name: tree-values-viewer
Version: 0.1.16
Summary: A tool to view project tree and file contents
Home-page: https://github.com/keskinbu/tree-values-viewer
Author: Burak Keskin
Author-email: me@burak.dev
License: UNKNOWN
Platform: UNKNOWN
Classifier: Programming Language :: Python :: 3
Classifier: License :: OSI Approved :: GNU Affero General Public License v3
Classifier: Operating System :: OS Independent
Requires-Python: >=3.6
License-File: LICENSE
Requires-Dist: prettytable
